<?xml version="1.0" encoding="UTF-8"?>
<!DOCTYPE suite SYSTEM "https://testng.org/testng-1.0.dtd">
<suite name="Suite" parallel="tests">
  <test thread-count="5" name="Test" >
    <classes>
      <class name="org.Automation.TestNG.DistributiveParallelExecution.SuryaKumarYadav"/>
      <class name="org.Automation.TestNG.DistributiveParallelExecution.RohitSharma"/>
      <class name="org.Automation.TestNG.DistributiveParallelExecution.KLRahul"/>
      <class name="org.Automation.TestNG.DistributiveParallelExecution.SachinTendulkar"/>
    </classes>
  </test> <!-- Test -->
  <test thread-count="5" name="Test2" >
    <classes>
      <class name="org.Automation.TestNG.DistributiveParallelExecution.HardikPandya"/>
      <class name="org.Automation.TestNG.DistributiveParallelExecution.RavindraJadeja"/>
    </classes>
  </test> <!-- Test -->
  <test thread-count="5" name="Test3" >
    <classes>
      <class name="org.Automation.TestNG.DistributiveParallelExecution.ViratKohli"/>
      <class name="org.Automation.TestNG.DistributiveParallelExecution.MSDhoni"/>
    </classes>
  </test> <!-- Test -->
</suite> <!-- Suite -->
